Workbook

Sheet Recall Monthly Cost
B2: Recall: monthly run cost. Production plan (Claude, paid) at top; capstone prototype (Gemini free tier) below.
B3: Blue = inputs (assumptions). Black = formulas. Prices per 1M tokens.
B4: Business days / month | C4: 22
B5: Call type | C5: Model | D5: Input tokens / call | E5: Output tokens / call | F5: Input $ / 1M | G5: Output $ / 1M | H5: Calls / day | I5: Cost / call ($) | J5: Cost / month ($) | K5: Why this model / note
B6: Signal extraction (capture) | C6: claude-haiku-5-5 | D6: =Inference!C11 -> 1840 | E6: =Inference!C12 -> 350 | F6: 0.1 | G6: 0.5 | H6: =Inference!C14 -> 60 | I6: =D6*F6/1000000+E6*G6/1000000 -> 0.000359 | J6: =I6*H6*$C$4 -> 0.47388 | K6: High volume, structured; links to Inference sheet
B7: Follow-up draft | C7: claude-sonnet-5-5 | D7: 3050 | E7: 300 | F7: 2 | G7: 10 | H7: 15 | I7: =D7*F7/1000000+E7*G7/1000000 -> 0.0091 | J7: =I7*H7*$C$4 -> 3.003 | K7: Client-facing writing quality; prompt = rules 250 + open items 300 + 4 excerpts x 600
B8: Ask the pipeline (Q&A) | C8: claude-sonnet-5-5 | D8: 3780 | E8: 300 | F8: 2 | G8: 10 | H8: 10 | I8: =D8*F8/1000000+E8*G8/1000000 -> 0.01056 | J8: =I8*H8*$C$4 -> 2.3232 | K8: Reasoning across 6 retrieved conversations with citations
B9: Monthly live eval re-run (55 sources) | C9: claude-haiku-5-5 | D9: =Inference!C11 -> 1840 | E9: =Inference!C12 -> 350 | F9: 0.1 | G9: 0.5 | H9: =55/C4 -> 2.5 | I9: =D9*F9/1000000+E9*G9/1000000 -> 0.000359 | J9: =I9*H9*$C$4 -> 0.019745 | K9: Regression check after prompt/model changes (55 calls/month)
B11: AI model cost / month | J11: =SUM(J6:J9) -> 5.819825
B13: Infrastructure
B14: Vercel hosting (Pro, 1 developer seat) | J14: 20 | K14: Hobby ($0) is personal/non-commercial only, so production uses Pro. Prototype runs on Hobby. Source: vercel.com/pricing
B15: Database for signals + approvals (Supabase free tier) | J15: 0 | K15: Prototype keeps state in the browser; v1 production fits a free Postgres tier
B16: Voice memo transcription | J16: 0 | K16: Phone's built-in dictation/transcription (iOS/Android); read.ai already licensed for Teams
B17: Channel connectors (Gmail, Slack, WhatsApp Business) | J17: 0 | K17: Gmail/Slack APIs free at this volume. WhatsApp Business Platform: user-initiated service conversations are free; verify per-message pricing before go-live
B18: Embeddings (v2 only) | J18: =Embeddings!D29 -> 0.05939 | K18: Shown for reference, NOT in the total: v1 uses per-account context, not vector search. See Embeddings sheet
B20: Total monthly run cost | J20: =J11+SUM(J14:J17) -> 25.819825
B21: Cost per seller per month (4 sellers) | J21: =J20/4 -> 6.4549563
B22: AI cost per captured message (all calls / messages) | J22: =J11/(H6*C4) -> 0.0044089583
B24: How cost shaped scope
B25: 1. Extraction on Haiku 5.5, not Sonnet: same structured job at 1/20th the price; the verbatim-quote check in code makes the cheaper model safe.
B26: 2. Ranking, dates, duplicates and CRM health are rules, not model calls: $0, instant, explainable.
B27: 3. Sonnet only where a client reads the output (drafts) or reasoning spans many messages (Q&A); both are on-demand, not per message.
B28: 4. No Opus: nothing in v1 needs it; it would double the Sonnet lines.
B29: 5. No embeddings / vector DB in v1: each call gets the account's own context; revisit when history exceeds what fits per account.
B30: 6. No call recording + speech-to-text for WhatsApp/FaceTime: platforms don't allow it and consent is unclear; post-call voice memos cost $0.
B31: 7. Sensitivity: even at 10x volume (600 messages/day) and drafts for every message, AI cost stays under ~$100/month.
B33: Source: Anthropic pricing page, platform.claude.com/docs/en/about-claude/pricing (checked 14 Oct 2026). Haiku 5.5 rate applies to prompts <=100K tokens.
B35: Sensitivity: 10x volume
B36: Volume multiplier | C36: 10
B37: AI model cost / month at multiplier | J37: =J11*C36 -> 58.19825
B39: Prototype deployment (capstone): Gemini free tier on Vercel Hobby
B40: Call type | C40: Model | F40: Input $ / 1M | G40: Output $ / 1M | J40: Cost / month ($) | K40: Note
B41: Signal extraction | C41: gemini-3.5-flash-lite | F41: 0 | G41: 0 | J41: 0 | K41: Free of charge on the free tier; limits are per project per minute and per day (AI Studio).
B42: Follow-up draft | C42: gemini-3.8-flash | F42: 0 | G42: 0 | J42: 0
B43: Ask the pipeline | C43: gemini-3.8-flash | F43: 0 | G43: 0 | J43: 0
B44: Hosting (Vercel Hobby) | C44: n/a | F44: 0 | G44: 0 | J44: 0 | K44: Hobby is free for personal, non-commercial use: fine for a capstone.
B45: Prototype monthly run cost | J45: =SUM(J41:J44) -> 0
B46: Why only for the prototype: Google states free-tier content is used to improve its products. The AtliQ dataset is synthetic, so this is acceptable for the capstone; real client messages must use a paid tier that does not train on inputs (the Claude plan above, or Gemini paid).
B48: Source: ai.google.dev/gemini-api/docs/pricing and /rate-limits (checked 14 Oct 2026); vercel.com/pricing.

Sheet Inference
B2: Recall: signal extraction call (one per incoming message, note, chat or voice memo). Model comparison.
B4: Base Calculation | E4: Model Selection + Cost Estimation
B5: Description | C5: Quantity | E5: Model Name | F5: Input cost($) per 1M token | G5: Output cost($) per 1M token | H5: Cost per input Query($) | I5: Cost per output query Query($) | J5: Total Cost per query | K5: Total cost per month
B6: Incoming message / note / transcript (avg 400 words x 1.3) | C6: 520 | E6: claude-haiku-5-5 | F6: 0.1 | G6: 0.5 | H6: =F6*$C$11/1000000 -> 0.000184 | I6: =G6*$C$12/1000000 -> 0.000175 | J6: =H6+I6 -> 0.000359 | K6: =Table2[[#This Row],[Total Cost per query]]*$C$16 -> 0.47388
B7: System prompt (rules) | C7: 600 | E7: claude-sonnet-5-5 | F7: 2 | G7: 10 | H7: =F7*$C$11/1000000 -> 0.00368 | I7: =G7*$C$12/1000000 -> 0.0035 | J7: =H7+I7 -> 0.00718 | K7: =Table2[[#This Row],[Total Cost per query]]*$C$16 -> 9.4776
B8: Tool schema (record_signals JSON schema) | C8: 500 | E8: claude-opus-5-5 | F8: 4 | G8: 20 | H8: =F8*$C$11/1000000 -> 0.00736 | I8: =G8*$C$12/1000000 -> 0.007 | J8: =H8+I8 -> 0.01436 | K8: =Table2[[#This Row],[Total Cost per query]]*$C$16 -> 18.9552
B9: Known-accounts list (company names) | C9: 200 | E9: gemini-3.5-flash-lite (free tier) | F9: 0 | G9: 0 | H9: =F9*$C$11/1000000 -> 0 | I9: =G9*$C$12/1000000 -> 0 | J9: =H9+I9 -> 0 | K9: =J9*$C$16 -> 0
B10: Message metadata (channel, date) | C10: 20
B11: Total input tokens per query | C11: =SUM(C6:C10) -> 1840
B12: Total Output tokens per query | C12: 350
B13: Total Token per query | C13: =C11+C12 -> 2190
B14: Total queries received per day | C14: 60
B15: Total number of days per month | C15: 22 | E15: Prototype: gemini-3.5-flash-lite on the free tier ($0; synthetic data only). Production: claude-haiku-5-5. Extraction is narrow and schema-bound, and Haiku is the vendor's recommended tier for extraction; Sonnet would cost 20x for the same job. Quote check in code catches any extraction slip.
B16: Total monthly volume of queries | C16: =C14*C15 -> 1320
E18: Source: Anthropic pricing page, platform.claude.com/docs/en/about-claude/pricing (checked 14 Oct 2026). Haiku 5.5 rate applies to prompts <=100K tokens.

Sheet Embeddings
C1: v2 option only: embeddings for search across all historical conversations. v1 does not use embeddings ($0).
C3: Token/word | D3: 1.3
C5: Email threads | F5: Meeting notes / call summaries | I5: Chat messages (WhatsApp/iMessage/Slack)
C6: Component | D6: Quantity | F6: Component | G6: Quantity | I6: Component | J6: Quantity
C7: Threads per year | D7: 6000 | F7: Notes per year | G7: 1500 | I7: Chats per year | J7: 8000
C8: Words per thread | D8: 250 | F8: Words per note | G8: 200 | I8: Words per chat | J8: 60
C9: Total number of words | D9: =D7*D8 -> 1500000 | F9: Total number of words | G9: =G8*G7 -> 300000 | I9: Total number of words | J9: =J8*J7 -> 480000
C10: Total Tokens | D10: =D9*D3 -> 1950000 | F10: Total tokens | G10: =G9*D3 -> 390000 | I10: Total tokens | J10: =J9*D3 -> 624000
C13: RAG Embeddings
C14: Component | D14: Cost/Quantity
C15: Total tokens for RAG | D15: =D10+G10+J10 -> 2964000
C16: Cost per 1M token | D16: 0.02
C17: Total cost for RAG | D17: =D15*D16/1000000 -> 0.05928
C20: User Query Embeddings
C21: Component | D21: Cost/Quantity
C22: Tokens per question | D22: 25
C23: Questions per month | D23: =10*22 -> 220
C24: Token tokens per month | D24: =D23*D22 -> 5500
C25: Cost per 1M token | D25: 0.02
C26: Total cost for user query embeddings | D26: =D24*D25/1000000 -> 0.00011
C29: Total cost of Embeddings | D29: =D17+D26 -> 0.05939

Sheet Cost Savings
D3: Alternative: hire a sales-ops coordinator to log every conversation
D4: Component | E4: Quantity
D5: Messages / notes per day to log | E5: ='Recall Monthly Cost'!H6 -> 60
D6: Items one coordinator can log per day | E6: 120
D7: Business days per month | E7: ='Recall Monthly Cost'!C4 -> 22
D8: Items one coordinator logs per month | E8: =E6*E7 -> 2640
D9: Total items per month | E9: =E5*E7 -> 1320
D10: Coordinators required | E10: =E9/E8 -> 0.5
D13: Monthly cost of coordinator ($)
D14: Component | E14: Cost
D15: Salary (Hyderabad, sales ops coordinator) | E15: 550
D16: Admin, tools, management overhead | E16: 120
D17: Total cost per human agent per month | E17: =E15+E16 -> 670
D19: Total cost for Human agent per month | E19: =E17*E10 -> 335
D22: Cost for Recall
D23: Component | E23: Cost
D24: AI model cost (Recall Monthly Cost sheet) | E24: ='Recall Monthly Cost'!J11 -> 5.819825
D25: Infrastructure (hosting, DB, connectors) | E25: =SUM('Recall Monthly Cost'!J14:J17) -> 20
D27: Total Recall cost | E27: =E24+E25 -> 25.819825
D30: Total savings vs coordinator | E30: =E19-E27 -> 309.18018
D31: % savings | E31: =E30/E19 -> 0.9229259
D34: Founder time and revenue at stake (the real case)
D35: Founder/seller hours on CRM upkeep + reconciliation per month (today: mostly not done) | E35: 30
D36: Blended founder hour value ($) | E36: 60
D37: Value of time returned per month ($) | E37: =E35*E36 -> 1800
D38: Known deal value currently waiting on AtliQ ($) | E38: 663000
D39: Share of that value saved by replying within 2 business days | E39: 0.1
D40: Revenue protected ($) | E40: =E38*E39 -> 66300
D41: Payback: months of Recall cost covered by one saved $20k deal | E41: =20000/E27 -> 774.59859
